parnoid/__init__.py
parnoid/parnoid.py
parnoid-0.4.0.dist-info/METADATA
parnoid-0.4.0.dist-info/WHEEL
parnoid-0.4.0.dist-info/licenses/LICENSE
parnoid-0.4.0.dist-info/RECORD
