Metadata-Version: 2.4
Name: parnoid
Version: 0.4.0
Summary: Parnoid SDK for Python
Project-URL: Homepage, https://www.parnoid.io
License-Expression: LicenseRef-Proprietary
License-File: LICENSE
Classifier: Operating System :: OS Independent
Classifier: Programming Language :: Python :: 3
Requires-Python: >=3.8
Requires-Dist: cryptography>=44.0.0
Requires-Dist: requests>=2.32.3
Provides-Extra: test
Requires-Dist: boto3>=1.39.6; extra == 'test'
